jsonfield/jsonfield.py
peewee_jsonfield-0.0.4.dist-info/LICENSE
peewee_jsonfield-0.0.4.dist-info/METADATA
peewee_jsonfield-0.0.4.dist-info/WHEEL
peewee_jsonfield-0.0.4.dist-info/top_level.txt
peewee_jsonfield-0.0.4.dist-info/RECORD
