Metadata-Version: 2.1
Name: peewee-jsonfield
Version: 0.0.4
Summary: JSONField for Peewee
Author: Mark Smirnov
Author-email: Mark Smirnov <mark@mark99.ru>
License: MIT License
Project-URL: Source code, https://github.com/mark99i/jsonfield
Platform: any
Classifier: Programming Language :: Python :: 3
Classifier: License :: OSI Approved :: MIT License
Classifier: Operating System :: OS Independent
Requires-Python: >=3.8
License-File: LICENSE
Requires-Dist: peewee
Requires-Dist: pymysql
